{"child_modules": [], "data_mtime": 1582804125, "dep_lines": [3, 5, 7, 1, 1, 1, 4, 6, 8, 9, 10, 11, 12, 13, 14, 15], "dep_prios": [10, 10, 5, 5, 30, 30, 10, 10, 5, 5, 5, 5, 5, 5, 5, 5], "dependencies": ["math", "threading", "time", "builtins", "abc", "typing"], "hash": "ef6ca063bd0081c85f60ca5a330c0179", "id": "pioneer_kinematics.kinematics", "ignore_all": false, "interface_hash": "5da5568f17ae142906e6f3ef6be0a4b1", "mtime": 1575987410, "options": {"allow_redefinition": false, "allow_untyped_globals": false, "always_false": [], "always_true": [], "bazel": false, "check_untyped_defs": false, "disallow_any_decorated": false, "disallow_any_explicit": false, "disallow_any_expr": false, "disallow_any_generics": false, "disallow_any_unimported": false, "disallow_incomplete_defs": false, "disallow_subclassing_any": false, "disallow_untyped_calls": false, "disallow_untyped_decorators": false, "disallow_untyped_defs": false, "follow_imports": "silent", "follow_imports_for_stubs": false, "ignore_errors": false, "ignore_missing_imports": true, "implicit_reexport": true, "local_partial_types": false, "mypyc": false, "new_semantic_analyzer": true, "no_implicit_optional": false, "platform": "linux", "plugins": [], "show_none_errors": true, "strict_equality": false, "strict_optional": true, "strict_optional_whitelist": null, "warn_no_return": true, "warn_return_any": false, "warn_unreachable": false, "warn_unused_ignores": false}, "path": "/home/ahan/catkin_ws/src/PIONEER-ROBOT/pioneer_kinematics/src/pioneer_kinematics/kinematics.py", "size": 14831, "suppressed": ["rospy", "numpy", "scipy.stats", "std_msgs.msg", "pioneer_utils.utils", "sensor_msgs.msg", "geometry_msgs.msg", "robotis_controller_msgs.msg", "thormang3_manipulation_module_msgs.srv", "thormang3_manipulation_module_msgs.msg"], "version_id": "0.720"}