{
    "0.15,0.1": [
        173.0,
        447.0
    ],
    "0.15,0.1156": [
        156.0,
        447.0
    ],
    "0.15,0.1311": [
        139.0,
        448.0
    ],
    "0.15,0.1467": [
        121.0,
        448.0
    ],
    "0.15,0.1622": [
        106.0,
        447.0
    ],
    "0.15,0.1778": [
        90.0,
        447.0
    ],
    "0.15,0.1933": [
        74.0,
        447.0
    ],
    "0.15,0.2089": [
        56.0,
        446.0
    ],
    "0.15,0.2244": [
        42.0,
        445.0
    ],
    "0.15,0.24": [
        27.0,
        444.0
    ],
    "0.1833,0.0944": [
        186.0,
        409.0
    ],
    "0.1833,0.2511": [
        23.0,
        408.0
    ],
    "0.2167,0.0889": [
        197.0,
        373.0
    ],
    "0.2167,0.2622": [
        23.0,
        372.0
    ],
    "0.25,0.0833": [
        207.0,
        340.0
    ],
    "0.25,0.2733": [
        22.0,
        337.0
    ],
    "0.2833,0.0778": [
        217.0,
        309.0
    ],
    "0.2833,0.2844": [
        22.0,
        306.0
    ],
    "0.3167,0.0722": [
        227.0,
        279.0
    ],
    "0.3167,0.2956": [
        23.0,
        276.0
    ],
    "0.35,0.0667": [
        235.0,
        252.0
    ],
    "0.35,0.3067": [
        23.0,
        247.0
    ],
    "0.3833,0.0611": [
        244.0,
        226.0
    ],
    "0.3833,0.3178": [
        23.0,
        220.0
    ],
    "0.4167,0.0556": [
        254.0,
        201.0
    ],
    "0.4167,0.3289": [
        23.0,
        194.0
    ],
    "0.45,0.05": [
        260.0,
        174.0
    ],
    "0.45,0.0822": [
        232.0,
        173.0
    ],
    "0.45,0.1144": [
        207.0,
        174.0
    ],
    "0.45,0.1467": [
        180.0,
        174.0
    ],
    "0.45,0.1789": [
        153.0,
        174.0
    ],
    "0.45,0.2111": [
        127.0,
        173.0
    ],
    "0.45,0.2433": [
        100.0,
        173.0
    ],
    "0.45,0.2756": [
        74.0,
        172.0
    ],
    "0.45,0.3078": [
        48.0,
        172.0
    ],
    "0.45,0.34": [
        23.0,
        171.0
    ]
}